adepy/__init__.py
adepy/_helpers.py
adepy/_version.py
adepy/chain_reaction.py
adepy/uniform/__init__.py
adepy/uniform/oneD.py
adepy/uniform/threeD.py
adepy/uniform/twoD.py
adepy-0.2.0.dist-info/licenses/LICENSE
tests/test_1D.py
tests/test_2D.py
tests/test_3D.py
tests/test_chain_reaction.py
adepy-0.2.0.dist-info/METADATA
adepy-0.2.0.dist-info/WHEEL
adepy-0.2.0.dist-info/top_level.txt
adepy-0.2.0.dist-info/RECORD
