Metadata-Version: 2.4
Name: adepy
Version: 0.2.0
Summary: Analytical solutions for solute transport in groundwater with Python
Author-email: Cas Neyens <cas.neyens@gmail.com>
License: MIT License
Project-URL: homepage, https://github.com/cneyens/adepy
Project-URL: repository, https://github.com/cneyens/adepy
Classifier: Programming Language :: Python :: 3 :: Only
Classifier: Programming Language :: Python :: 3.10
Classifier: Programming Language :: Python :: 3.11
Classifier: Programming Language :: Python :: 3.12
Classifier: Programming Language :: Python :: 3.13
Classifier: Topic :: Scientific/Engineering :: Hydrology
Classifier: Intended Audience :: Science/Research
Classifier: License :: OSI Approved :: MIT License
Classifier: Operating System :: OS Independent
Classifier: Typing :: Typed
Requires-Python: >=3.10
License-File: LICENSE
Requires-Dist: numpy
Requires-Dist: scipy
Requires-Dist: numba
Dynamic: license-file
